great_expectations/__init__.py
great_expectations/alias_types.py
great_expectations/util.py
great_expectations/checkpoint/__init__.py
great_expectations/checkpoint/actions.py
great_expectations/checkpoint/checkpoint.py
great_expectations/checkpoint/configurator.py
great_expectations/checkpoint/util.py
great_expectations/checkpoint/types/__init__.py
great_expectations/checkpoint/types/checkpoint_result.py
great_expectations/cli/__init__.py
great_expectations/cli/batch_request.py
great_expectations/cli/build_docs.py
great_expectations/cli/checkpoint.py
great_expectations/cli/checkpoint_script_template.py
great_expectations/cli/cli.py
great_expectations/cli/cli_logging.py
great_expectations/cli/cli_messages.py
great_expectations/cli/datasource.py
great_expectations/cli/docs.py
great_expectations/cli/init.py
great_expectations/cli/mark.py
great_expectations/cli/pretty_printing.py
great_expectations/cli/project.py
great_expectations/cli/python_subprocess.py
great_expectations/cli/store.py
great_expectations/cli/suite.py
great_expectations/cli/toolkit.py
great_expectations/cli/util.py
great_expectations/cli/validation_operator.py
great_expectations/cli/upgrade_helpers/__init__.py
great_expectations/cli/upgrade_helpers/base_upgrade_helper.py
great_expectations/cli/upgrade_helpers/upgrade_helper_v11.py
great_expectations/cli/upgrade_helpers/upgrade_helper_v13.py
great_expectations/cli/v012/__init__.py
great_expectations/cli/v012/checkpoint.py
great_expectations/cli/v012/checkpoint_script_template.py
great_expectations/cli/v012/cli.py
great_expectations/cli/v012/cli_logging.py
great_expectations/cli/v012/cli_messages.py
great_expectations/cli/v012/datasource.py
great_expectations/cli/v012/docs.py
great_expectations/cli/v012/init.py
great_expectations/cli/v012/mark.py
great_expectations/cli/v012/project.py
great_expectations/cli/v012/python_subprocess.py
great_expectations/cli/v012/store.py
great_expectations/cli/v012/suite.py
great_expectations/cli/v012/toolkit.py
great_expectations_cta-0.15.43.dist-info/LICENSE
great_expectations_cta-0.15.43.dist-info/METADATA
great_expectations_cta-0.15.43.dist-info/WHEEL
great_expectations_cta-0.15.43.dist-info/entry_points.txt
great_expectations_cta-0.15.43.dist-info/top_level.txt
great_expectations_cta-0.15.43.dist-info/RECORD
